jaxnrsur/DataLoader.py
jaxnrsur/EIMPredictor.py
jaxnrsur/Harmonics.py
jaxnrsur/Kernels.py
jaxnrsur/NRHybSur3dq8.py
jaxnrsur/NRSur7dq4.py
jaxnrsur/PolyPredictor.py
jaxnrsur/Spline.py
jaxnrsur/__init__.py
jaxnrsur/special_function.py
jaxnrsur-1.0.0.dist-info/METADATA
jaxnrsur-1.0.0.dist-info/WHEEL
jaxnrsur-1.0.0.dist-info/licenses/LICENSE
jaxnrsur-1.0.0.dist-info/RECORD
