Metadata-Version: 2.4
Name: JaxNRSur
Version: 1.0.0
Summary: Numerical relativity surrogate model for gravitational waveforms in Jax
Project-URL: Homepage, https://github.com/kazewong/JaxNRSur
Project-URL: Repository, https://github.com/kazewong/JaxNRSur
Author: Max isi, Ethan Payne, Vijay Varma, Tousif Islam
Author-email: "Kaze W. K. Wong" <kazewong.physics@gmail.com>
License: MIT
License-File: LICENSE
Keywords: Numerical relativity,autodiff,gravitational-wave,jax
Requires-Python: >=3.11
Requires-Dist: beartype>=0.21.0
Requires-Dist: coveralls>=4.0.1
Requires-Dist: equinox>=0.12.1
Requires-Dist: h5py>=3.13.0
Requires-Dist: jax>=0.6.0
Requires-Dist: lineax>=0.0.8
Requires-Dist: optax>=0.2.5
Requires-Dist: requests>=2.32.3
Provides-Extra: benchmark
Requires-Dist: gwsurrogate>=1.1.6; extra == 'benchmark'
Requires-Dist: tensorboard>=2.19.0; extra == 'benchmark'
Provides-Extra: cuda
Requires-Dist: jax[cuda]>=0.6.0; extra == 'cuda'
